{
  "plugin.description": "Zeigt konfigurierbare Spieler-Buff-Leisten, Ladungsicons und Rage-Status an.",
  "button.apply_watchlist": "Merkliste anwenden",
  "button.download_missing_icons": "Fehlende Symbole herunterladen",
  "button.dump_buffs": "Lass meine Buffs fallen",
  "button.reload_icons": "Symbole neu laden",
  "button.reset_defaults": "Standardeinstellungen zurücksetzen",
  "display_mode.icons": "Symbole",
  "display_mode.icons_and_text": "Symbole + Text",
  "display_mode.text": "Text",
  "hud.drag_hint": "Zum Verschieben ziehen. Deaktivieren Sie den Dummy in den Einstellungen, wenn Sie fertig sind.",
  "hud.inactive_suffix": "{0} – aus",
  "hud.rage_count": "Wut:{0}",
  "section.buff_bars": "Buff-Bars (bis zu 4)",
  "section.buff_display": "Buff-Anzeige",
  "section.colors": "Farben",
  "section.general": "Allgemein",
  "section.icons_tools": "Symbole und Werkzeuge",
  "section.resource_bar": "Ressourcenleiste (Ladungen / Wut)",
  "section.watchlist": "Beobachtungsliste",
  "settings.active_buff_color": "Aktive Buff-Farbe",
  "settings.anchor_resource_bar": "Verankern Sie die Ressourcenleiste in der Gesundheitsleiste",
  "settings.anchor_to_health_bar": "Anker zur Gesundheitsleiste",
  "settings.auto_download_icons": "poe2db-Symbole automatisch herunterladen",
  "settings.buff_bars_help": "Jeder Balken hat seine eigene Beobachtungsliste und Position. Ressourcenladungen/Wut bleiben auf der Ressourcenleiste.",
  "settings.buff_text_color": "Textfarbe verstärken",
  "settings.charge_text_color": "Textfarbe berechnen",
  "settings.count_badge_background": "Hintergrund des Zählabzeichens",
  "settings.count_badge_background.tooltip": "Wenn diese Option deaktiviert ist, werden die Anzahl der Ladungen/Wut und Buff-Stapel nur als Text angezeigt (kein schwarzer Balken auf dem Symbol).",
  "settings.display_mode": "Anzeigemodus",
  "settings.enable_this_bar": "Aktivieren Sie diese Leiste",
  "settings.fixed_position": "Feste Position",
  "settings.font_scale": "Schriftskala",
  "settings.hide_background": "Beim Spielen im Hintergrund ausblenden",
  "settings.hide_empty_resources": "Leere Anklagen / Wut verbergen",
  "settings.hide_town_hideout": "Verstecke dich in der Stadt / im Versteck",
  "settings.icon_size": "Symbolgröße",
  "settings.icon_spacing": "Symbolabstand",
  "settings.icons_help": "Symbole werden von poe2db.tw (PoE2) geladen. Cache: Plugins/PlayerBuffBar/icons/.",
  "settings.inactive_buff_color": "Inaktive Buff-Farbe",
  "settings.inactive_icon_alpha": "Inaktives Symbol Alpha",
  "settings.max_bar_width": "Maximale Balkenbreite",
  "settings.offset": "Versatz X/Y",
  "settings.offset_help": "Positives Y = unteres Zeichen, negatives Y = darüber.",
  "settings.rage_text_color": "Wut-Textfarbe",
  "settings.resource_fixed_position": "Feste Position der Ressource",
  "settings.resource_help": "P/F/E-Ladesymbole werden von poe2db geladen. Wut bleibt numerisch. Fügen Sie der Beobachtungsliste keine Anklage/Wut hinzu.",
  "settings.resource_icon_size": "Größe des Ressourcensymbols",
  "settings.resource_icon_spacing": "Abstand der Ressourcensymbole",
  "settings.resource_offset": "Ressourcenoffset X/Y",
  "settings.show_charges": "Gebühren anzeigen (P/F/E)",
  "settings.show_durations": "Dauer anzeigen",
  "settings.show_inactive_watchlist": "Inaktive Watchlist-Buffs anzeigen",
  "settings.show_overlay": "Overlay anzeigen",
  "settings.show_position_dummy": "Positionsdummy anzeigen (ziehen, dann deaktivieren)",
  "settings.show_rage": "Zeige Wut",
  "settings.show_stacks": "Stapel anzeigen",
  "settings.watchlist_help": "Ein Buff-ID-Teilstring pro Zeile. Nicht wegen Anklage/Wut. Beispiele: puppet_master, widerlegung, archon_undeath.",
  "status.cached_icons": "Zwischengespeicherte Symbole: {0}",
  "status.dump_failed_buffs": "Dump fehlgeschlagen: Spieler-Buffs nicht lesbar.",
  "status.dump_failed_error": "Dump fehlgeschlagen: {0}",
  "status.dump_failed_state": "Dump ist fehlgeschlagen: Geben Sie zuerst eine Karte oder Stadt ein.",
  "status.dump_saved": "Dump gespeichert ({0} Buffs): Plugins/PlayerBuffBar/player_buff_dump.txt",
  "tab.bar": "Leiste {0}",
  "tab.off_suffix": "(aus)"
}
